dop_python_pip_package/__init__.py
dop_python_pip_package/main_utils/__init__.py
dop_python_pip_package/main_utils/math.py
dop_python_pip_package-0.0.4.dist-info/LICENSE.txt
dop_python_pip_package-0.0.4.dist-info/METADATA
dop_python_pip_package-0.0.4.dist-info/WHEEL
dop_python_pip_package-0.0.4.dist-info/top_level.txt
dop_python_pip_package-0.0.4.dist-info/RECORD
